{"skeleton":{"hash":"ASBcZQfLR5k","spine":"4.0.64","x":-97.42,"y":-0.54,"width":192,"height":184,"images":"./images/","audio":""},"bones":[{"name":"root"},{"name":"cake","parent":"root","x":1.4,"y":-0.28}],"slots":[{"name":"cake","bone":"cake","attachment":"cake"}],"skins":[{"name":"default","attachments":{"cake":{"cake":{"x":-2.82,"y":91.74,"width":192,"height":184}}}}],"animations":{"drop":{"bones":{"cake":{"translate":[{"y":120.18,"curve":[0.058,0,0.198,0,0.058,120.18,0.198,48.25]},{"time":0.2333,"y":3.23}],"scale":[{"x":0.946,"y":1.054,"curve":"stepped"},{"time":0.1333,"x":0.946,"y":1.054,"curve":[0.175,0.946,0.258,1.146,0.175,1.054,0.258,0.905]},{"time":0.3,"x":1.146,"y":0.905,"curve":[0.333,1.146,0.4,0.99,0.333,0.905,0.4,1.031]},{"time":0.4333,"x":0.99,"y":1.031,"curve":[0.467,0.99,0.533,1,0.467,1.031,0.533,1]},{"time":0.5667}]}}},"idle":{"bones":{"cake":{"translate":[{"y":3.23}]}}}}}